blue_interface/__init__.py
blue_interface/blue_interface.py
blue_interface/rosbridge_client.py
blue_interface-0.1.dist-info/LICENSE
blue_interface-0.1.dist-info/METADATA
blue_interface-0.1.dist-info/WHEEL
blue_interface-0.1.dist-info/top_level.txt
blue_interface-0.1.dist-info/RECORD
