Metadata-Version: 2.1
Name: blue-interface
Version: 0.1
Summary: Python API for controlling the Blue robot arm
Home-page: http://github.com/berkeleyopenarms/blue_interface
Author: Rachel Thomasson, Brent Yi, Philipp Wu, Greg Balke
Author-email: brentyi@berkeley.edu
License: BSD
Platform: UNKNOWN
Classifier: Programming Language :: Python :: 2.7
Classifier: Programming Language :: Python :: 3.5
Classifier: Programming Language :: Python :: 3.6
Classifier: Programming Language :: Python :: 3.7
Classifier: Programming Language :: Python :: 3.8
Classifier: License :: OSI Approved :: MIT License
Classifier: Operating System :: OS Independent
Requires-Dist: ws4py
Requires-Dist: PyDispatcher
Requires-Dist: numpy
Requires-Dist: enum34
Requires-Dist: typing
